lotr/__init__.py
lotr/_book.py
lotr/_chapter.py
lotr/_character.py
lotr/_movie.py
lotr/_quote.py
vinodmsdk-0.0.3.dist-info/LICENSE
vinodmsdk-0.0.3.dist-info/METADATA
vinodmsdk-0.0.3.dist-info/WHEEL
vinodmsdk-0.0.3.dist-info/top_level.txt
vinodmsdk-0.0.3.dist-info/RECORD
