Metadata-Version: 2.1
Name: vinodmsdk
Version: 0.0.3
Summary: SDK for Lord of the Rings API
Author-email: VinodM <vinodm@example.com>
Project-URL: Homepage, https://github.com/vinod-m/vinodm-sdk
Project-URL: Bug Tracker, https://github.com/vinod-m/vinodm-sdk/issues
Classifier: Programming Language :: Python :: 3
Classifier: License :: OSI Approved :: MIT License
Classifier: Operating System :: OS Independent
Requires-Python: >=3.8
License-File: LICENSE
